__init__.py
absurdsortlib.py
asurdsortlib-1.0.0.dist-info/licenses/LICENSE.txt
asurdsortlib-1.0.0.dist-info/METADATA
asurdsortlib-1.0.0.dist-info/WHEEL
asurdsortlib-1.0.0.dist-info/top_level.txt
asurdsortlib-1.0.0.dist-info/RECORD
