Metadata-Version: 2.4
Name: asurdsortlib
Version: 1.0.0
Summary: Very useful sorting algorithms, ignore the title, they are extremely fast and useful
Author-email: Polecat <polecat@disroot.org>
License-Expression: MIT
Keywords: sort,joke,sorting
License-File: LICENSE.txt
Dynamic: license-file
